{
  "address": "0x023a3d058020fb76cca98f01b3c48c8938a22355",
  "positions": [
    {
      "coin": "kPEPE",
      "size": -623205884.0,
      "entry_price": 0.007846,
      "mark_price": 0.0,
      "unrealized_pnl": -78703.921882,
      "position_value": 4968820.513132,
      "leverage": {
        "type": "cross",
        "value": 10
      },
      "timestamp": "2025-03-25T15:16:46.222615"
    },
    {
      "coin": "BTC",
      "size": 42.69404,
      "entry_price": 87216.1,
      "mark_price": 0.0,
      "unrealized_pnl": 24243.550553,
      "position_value": 3747853.60736,
      "leverage": {
        "type": "cross",
        "value": 40
      },
      "timestamp": "2025-03-25T15:16:46.222563"
    },
    {
      "coin": "SOL",
      "size": -17189.66,
      "entry_price": 143.5914,
      "mark_price": 0.0,
      "unrealized_pnl": -40370.744715,
      "position_value": 2508658.9804,
      "leverage": {
        "type": "cross",
        "value": 20
      },
      "timestamp": "2025-03-25T15:16:46.222587"
    },
    {
      "coin": "ETH",
      "size": 905.7572,
      "entry_price": 2056.79,
      "mark_price": 0.0,
      "unrealized_pnl": 7703.971267,
      "position_value": 1870660.34516,
      "leverage": {
        "type": "cross",
        "value": 25
      },
      "timestamp": "2025-03-25T15:16:46.222577"
    },
    {
      "coin": "ONDO",
      "size": -923993.0,
      "entry_price": 0.911355,
      "mark_price": 0.0,
      "unrealized_pnl": -16765.383905,
      "position_value": 858851.4935,
      "leverage": {
        "type": "cross",
        "value": 10
      },
      "timestamp": "2025-03-25T15:16:46.222765"
    },
    {
      "coin": "AI16Z",
      "size": -3430437.5,
      "entry_price": 0.20136,
      "mark_price": 0.0,
      "unrealized_pnl": -34626.449631,
      "position_value": 725400.31375,
      "leverage": {
        "type": "cross",
        "value": 5
      },
      "timestamp": "2025-03-25T15:16:46.222917"
    },
    {
      "coin": "NIL",
      "size": -1019463.0,
      "entry_price": 0.732951,
      "mark_price": 0.0,
      "unrealized_pnl": 26201.524817,
      "position_value": 721015.20675,
      "leverage": {
        "type": "cross",
        "value": 3
      },
      "timestamp": "2025-03-25T15:16:46.222967"
    },
    {
      "coin": "ENA",
      "size": -1428755.0,
      "entry_price": 0.426746,
      "mark_price": 0.0,
      "unrealized_pnl": -5519.58268,
      "position_value": 615236.19055,
      "leverage": {
        "type": "cross",
        "value": 10
      },
      "timestamp": "2025-03-25T15:16:46.222800"
    },
    {
      "coin": "TAO",
      "size": -1960.349,
      "entry_price": 269.383,
      "mark_price": 0.0,
      "unrealized_pnl": -4031.150209,
      "position_value": 532117.13256,
      "leverage": {
        "type": "cross",
        "value": 5
      },
      "timestamp": "2025-03-25T15:16:46.222783"
    },
    {
      "coin": "OM",
      "size": 78076.6,
      "entry_price": 6.71959,
      "mark_price": 0.0,
      "unrealized_pnl": 2553.587151,
      "position_value": 527196.62618,
      "leverage": {
        "type": "cross",
        "value": 5
      },
      "timestamp": "2025-03-25T15:16:46.222962"
    },
    {
      "coin": "JTO",
      "size": -218819.0,
      "entry_price": 2.250121,
      "mark_price": 0.0,
      "unrealized_pnl": -24371.690686,
      "position_value": 516741.0685,
      "leverage": {
        "type": "cross",
        "value": 3
      },
      "timestamp": "2025-03-25T15:16:46.222746"
    },
    {
      "coin": "MKR",
      "size": -397.3721,
      "entry_price": 1253.44,
      "mark_price": 0.0,
      "unrealized_pnl": -3915.749528,
      "position_value": 502000.17393,
      "leverage": {
        "type": "cross",
        "value": 10
      },
      "timestamp": "2025-03-25T15:16:46.222645"
    },
    {
      "coin": "BNB",
      "size": -685.15,
      "entry_price": 637.611,
      "mark_price": 0.0,
      "unrealized_pnl": 2789.782467,
      "position_value": 434069.931,
      "leverage": {
        "type": "cross",
        "value": 10
      },
      "timestamp": "2025-03-25T15:16:46.222593"
    },
    {
      "coin": "RUNE",
      "size": -342915.8,
      "entry_price": 1.22719,
      "mark_price": 0.0,
      "unrealized_pnl": -8779.912818,
      "position_value": 429604.91424,
      "leverage": {
        "type": "cross",
        "value": 5
      },
      "timestamp": "2025-03-25T15:16:46.222668"
    },
    {
      "coin": "POPCAT",
      "size": -1578121.0,
      "entry_price": 0.230193,
      "mark_price": 0.0,
      "unrealized_pnl": -31035.345522,
      "position_value": 394309.31306,
      "leverage": {
        "type": "cross",
        "value": 10
      },
      "timestamp": "2025-03-25T15:16:46.222813"
    },
    {
      "coin": "BLAST",
      "size": -103287337.0,
      "entry_price": 0.003319,
      "mark_price": 0.0,
      "unrealized_pnl": -32227.961889,
      "position_value": 375139.607984,
      "leverage": {
        "type": "cross",
        "value": 3
      },
      "timestamp": "2025-03-25T15:16:46.222846"
    },
    {
      "coin": "BERA",
      "size": 42333.1,
      "entry_price": 7.94451,
      "mark_price": 0.0,
      "unrealized_pnl": 7674.502658,
      "position_value": 343990.30398,
      "leverage": {
        "type": "cross",
        "value": 5
      },
      "timestamp": "2025-03-25T15:16:46.222951"
    },
    {
      "coin": "FARTCOIN",
      "size": 609542.8,
      "entry_price": 0.38841,
      "mark_price": 0.0,
      "unrealized_pnl": 105891.911686,
      "position_value": 342648.389592,
      "leverage": {
        "type": "cross",
        "value": 3
      },
      "timestamp": "2025-03-25T15:16:46.222915"
    },
    {
      "coin": "LINK",
      "size": -20796.0,
      "entry_price": 15.29323,
      "mark_price": 0.0,
      "unrealized_pnl": -1721.111107,
      "position_value": 319759.296,
      "leverage": {
        "type": "cross",
        "value": 10
      },
      "timestamp": "2025-03-25T15:16:46.222623"
    },
    {
      "coin": "ZK",
      "size": -3872935.0,
      "entry_price": 0.077557,
      "mark_price": 0.0,
      "unrealized_pnl": -11745.744118,
      "position_value": 312119.83165,
      "leverage": {
        "type": "cross",
        "value": 5
      },
      "timestamp": "2025-03-25T15:16:46.222843"
    },
    {
      "coin": "WIF",
      "size": -577572.0,
      "entry_price": 0.543491,
      "mark_price": 0.0,
      "unrealized_pnl": 1825.898184,
      "position_value": 312079.47876,
      "leverage": {
        "type": "cross",
        "value": 10
      },
      "timestamp": "2025-03-25T15:16:46.222749"
    },
    {
      "coin": "AAVE",
      "size": -1405.47,
      "entry_price": 188.4019,
      "mark_price": 0.0,
      "unrealized_pnl": 705.522736,
      "position_value": 264087.813,
      "leverage": {
        "type": "cross",
        "value": 10
      },
      "timestamp": "2025-03-25T15:16:46.222642"
    },
    {
      "coin": "CAKE",
      "size": -92610.6,
      "entry_price": 2.61301,
      "mark_price": 0.0,
      "unrealized_pnl": 3149.915812,
      "position_value": 238842.7374,
      "leverage": {
        "type": "cross",
        "value": 3
      },
      "timestamp": "2025-03-25T15:16:46.222751"
    },
    {
      "coin": "AIXBT",
      "size": -1943111.0,
      "entry_price": 0.112835,
      "mark_price": 0.0,
      "unrealized_pnl": -18001.367147,
      "position_value": 237253.8531,
      "leverage": {
        "type": "cross",
        "value": 5
      },
      "timestamp": "2025-03-25T15:16:46.222920"
    },
    {
      "coin": "TRUMP",
      "size": -19600.0,
      "entry_price": 11.50536,
      "mark_price": 0.0,
      "unrealized_pnl": -816.12338,
      "position_value": 226321.2,
      "leverage": {
        "type": "cross",
        "value": 10
      },
      "timestamp": "2025-03-25T15:16:46.222939"
    },
    {
      "coin": "HYPE",
      "size": -13439.17,
      "entry_price": 16.53,
      "mark_price": 0.0,
      "unrealized_pnl": -1571.066301,
      "position_value": 223721.86299,
      "leverage": {
        "type": "cross",
        "value": 3
      },
      "timestamp": "2025-03-25T15:16:46.222899"
    },
    {
      "coin": "HBAR",
      "size": -1087396.0,
      "entry_price": 0.188864,
      "mark_price": 0.0,
      "unrealized_pnl": -11326.114006,
      "position_value": 216696.27488,
      "leverage": {
        "type": "cross",
        "value": 5
      },
      "timestamp": "2025-03-25T15:16:46.222810"
    },
    {
      "coin": "VIRTUAL",
      "size": -258657.9,
      "entry_price": 0.78535,
      "mark_price": 0.0,
      "unrealized_pnl": -6870.184572,
      "position_value": 210009.522168,
      "leverage": {
        "type": "cross",
        "value": 5
      },
      "timestamp": "2025-03-25T15:16:46.222907"
    },
    {
      "coin": "DYDX",
      "size": 282047.2,
      "entry_price": 0.68677,
      "mark_price": 0.0,
      "unrealized_pnl": 11518.422385,
      "position_value": 205220.363192,
      "leverage": {
        "type": "cross",
        "value": 5
      },
      "timestamp": "2025-03-25T15:16:46.222584"
    },
    {
      "coin": "TIA",
      "size": -54805.9,
      "entry_price": 3.64805,
      "mark_price": 0.0,
      "unrealized_pnl": -265.743684,
      "position_value": 200200.47211,
      "leverage": {
        "type": "cross",
        "value": 10
      },
      "timestamp": "2025-03-25T15:16:46.222692"
    },
    {
      "coin": "MOVE",
      "size": 423931.0,
      "entry_price": 0.447023,
      "mark_price": 0.0,
      "unrealized_pnl": 824.99798,
      "position_value": 190332.30107,
      "leverage": {
        "type": "cross",
        "value": 5
      },
      "timestamp": "2025-03-25T15:16:46.222904"
    },
    {
      "coin": "XRP",
      "size": 76908.0,
      "entry_price": 2.436444,
      "mark_price": 0.0,
      "unrealized_pnl": 604.142403,
      "position_value": 187986.2244,
      "leverage": {
        "type": "cross",
        "value": 20
      },
      "timestamp": "2025-03-25T15:16:46.222634"
    },
    {
      "coin": "RENDER",
      "size": -45654.7,
      "entry_price": 3.49449,
      "mark_price": 0.0,
      "unrealized_pnl": -26790.330703,
      "position_value": 186330.52711,
      "leverage": {
        "type": "cross",
        "value": 5
      },
      "timestamp": "2025-03-25T15:16:46.222851"
    },
    {
      "coin": "JUP",
      "size": -313234.0,
      "entry_price": 0.564742,
      "mark_price": 0.0,
      "unrealized_pnl": -3585.855538,
      "position_value": 180482.29846,
      "leverage": {
        "type": "cross",
        "value": 10
      },
      "timestamp": "2025-03-25T15:16:46.222739"
    },
    {
      "coin": "POL",
      "size": -777539.0,
      "entry_price": 0.215008,
      "mark_price": 0.0,
      "unrealized_pnl": -6929.227865,
      "position_value": 174106.53288,
      "leverage": {
        "type": "cross",
        "value": 5
      },
      "timestamp": "2025-03-25T15:16:46.222856"
    },
    {
      "coin": "ARB",
      "size": 443534.0,
      "entry_price": 0.38825,
      "mark_price": 0.0,
      "unrealized_pnl": 38.596034,
      "position_value": 172241.99356,
      "leverage": {
        "type": "cross",
        "value": 10
      },
      "timestamp": "2025-03-25T15:16:46.222604"
    },
    {
      "coin": "APT",
      "size": -28908.39,
      "entry_price": 5.9303,
      "mark_price": 0.0,
      "unrealized_pnl": -580.02114,
      "position_value": 172016.483856,
      "leverage": {
        "type": "cross",
        "value": 10
      },
      "timestamp": "2025-03-25T15:16:46.222640"
    },
    {
      "coin": "AVAX",
      "size": -7449.33,
      "entry_price": 22.2856,
      "mark_price": 0.0,
      "unrealized_pnl": -1432.591902,
      "position_value": 167446.03974,
      "leverage": {
        "type": "cross",
        "value": 10
      },
      "timestamp": "2025-03-25T15:16:46.222590"
    },
    {
      "coin": "SAGA",
      "size": -420828.1,
      "entry_price": 0.44555,
      "mark_price": 0.0,
      "unrealized_pnl": 23061.709614,
      "position_value": 164438.580075,
      "leverage": {
        "type": "cross",
        "value": 5
      },
      "timestamp": "2025-03-25T15:16:46.222805"
    },
    {
      "coin": "LDO",
      "size": -153938.9,
      "entry_price": 1.04198,
      "mark_price": 0.0,
      "unrealized_pnl": -2912.24988,
      "position_value": 163313.77901,
      "leverage": {
        "type": "cross",
        "value": 10
      },
      "timestamp": "2025-03-25T15:16:46.222620"
    },
    {
      "coin": "IP",
      "size": -25493.3,
      "entry_price": 6.07652,
      "mark_price": 0.0,
      "unrealized_pnl": -1661.412051,
      "position_value": 156572.20061,
      "leverage": {
        "type": "cross",
        "value": 3
      },
      "timestamp": "2025-03-25T15:16:46.222959"
    },
    {
      "coin": "VVV",
      "size": -50376.01,
      "entry_price": 3.2984,
      "mark_price": 0.0,
      "unrealized_pnl": 11180.972907,
      "position_value": 154981.794765,
      "leverage": {
        "type": "cross",
        "value": 3
      },
      "timestamp": "2025-03-25T15:16:46.222949"
    },
    {
      "coin": "PENGU",
      "size": -21901615.0,
      "entry_price": 0.006735,
      "mark_price": 0.0,
      "unrealized_pnl": -6880.051174,
      "position_value": 154406.38575,
      "leverage": {
        "type": "cross",
        "value": 5
      },
      "timestamp": "2025-03-25T15:16:46.222910"
    },
    {
      "coin": "kSHIB",
      "size": -11128138.0,
      "entry_price": 0.013224,
      "mark_price": 0.0,
      "unrealized_pnl": -3162.599236,
      "position_value": 150330.016242,
      "leverage": {
        "type": "cross",
        "value": 10
      },
      "timestamp": "2025-03-25T15:16:46.222658"
    },
    {
      "coin": "SUSHI",
      "size": 215828.1,
      "entry_price": 0.65233,
      "mark_price": 0.0,
      "unrealized_pnl": 9175.29996,
      "position_value": 149968.155285,
      "leverage": {
        "type": "cross",
        "value": 5
      },
      "timestamp": "2025-03-25T15:16:46.222729"
    },
    {
      "coin": "LTC",
      "size": -1574.17,
      "entry_price": 93.1474,
      "mark_price": 0.0,
      "unrealized_pnl": -754.965646,
      "position_value": 147384.81459,
      "leverage": {
        "type": "cross",
        "value": 10
      },
      "timestamp": "2025-03-25T15:16:46.222601"
    },
    {
      "coin": "BRETT",
      "size": -3757324.0,
      "entry_price": 0.03545,
      "mark_price": 0.0,
      "unrealized_pnl": -6231.628278,
      "position_value": 139430.536316,
      "leverage": {
        "type": "cross",
        "value": 5
      },
      "timestamp": "2025-03-25T15:16:46.222837"
    },
    {
      "coin": "SUI",
      "size": -56843.4,
      "entry_price": 2.41934,
      "mark_price": 0.0,
      "unrealized_pnl": -418.186145,
      "position_value": 137941.87878,
      "leverage": {
        "type": "cross",
        "value": 10
      },
      "timestamp": "2025-03-25T15:16:46.222612"
    },
    {
      "coin": "MORPHO",
      "size": -91313.2,
      "entry_price": 1.36446,
      "mark_price": 0.0,
      "unrealized_pnl": -5829.343634,
      "position_value": 130422.64356,
      "leverage": {
        "type": "cross",
        "value": 3
      },
      "timestamp": "2025-03-25T15:16:46.222936"
    },
    {
      "coin": "SAND",
      "size": 425285.0,
      "entry_price": 0.287969,
      "mark_price": 0.0,
      "unrealized_pnl": 6166.844873,
      "position_value": 128635.95395,
      "leverage": {
        "type": "cross",
        "value": 3
      },
      "timestamp": "2025-03-25T15:16:46.222891"
    },
    {
      "coin": "CRV",
      "size": -242410.8,
      "entry_price": 0.50525,
      "mark_price": 0.0,
      "unrealized_pnl": -169.922363,
      "position_value": 122650.168368,
      "leverage": {
        "type": "cross",
        "value": 10
      },
      "timestamp": "2025-03-25T15:16:46.222618"
    },
    {
      "coin": "ZETA",
      "size": -399891.9,
      "entry_price": 0.32158,
      "mark_price": 0.0,
      "unrealized_pnl": 8988.584484,
      "position_value": 119611.666209,
      "leverage": {
        "type": "cross",
        "value": 3
      },
      "timestamp": "2025-03-25T15:16:46.222770"
    },
    {
      "coin": "S",
      "size": -193472.0,
      "entry_price": 0.607264,
      "mark_price": 0.0,
      "unrealized_pnl": -1361.199593,
      "position_value": 118849.8496,
      "leverage": {
        "type": "cross",
        "value": 5
      },
      "timestamp": "2025-03-25T15:16:46.222933"
    },
    {
      "coin": "W",
      "size": 1180762.6,
      "entry_price": 0.10323,
      "mark_price": 0.0,
      "unrealized_pnl": -3898.650061,
      "position_value": 117993.606618,
      "leverage": {
        "type": "cross",
        "value": 5
      },
      "timestamp": "2025-03-25T15:16:46.222775"
    },
    {
      "coin": "DOGE",
      "size": 622481.0,
      "entry_price": 0.186113,
      "mark_price": 0.0,
      "unrealized_pnl": 1541.5089,
      "position_value": 117393.69179,
      "leverage": {
        "type": "cross",
        "value": 10
      },
      "timestamp": "2025-03-25T15:16:46.222607"
    },
    {
      "coin": "kFLOKI",
      "size": -1716300.0,
      "entry_price": 0.062154,
      "mark_price": 0.0,
      "unrealized_pnl": -7853.382486,
      "position_value": 114528.699,
      "leverage": {
        "type": "cross",
        "value": 5
      },
      "timestamp": "2025-03-25T15:16:46.222792"
    },
    {
      "coin": "MELANIA",
      "size": 166473.1,
      "entry_price": 0.69028,
      "mark_price": 0.0,
      "unrealized_pnl": -1934.943942,
      "position_value": 112978.634046,
      "leverage": {
        "type": "cross",
        "value": 5
      },
      "timestamp": "2025-03-25T15:16:46.222941"
    },
    {
      "coin": "BCH",
      "size": -327.031,
      "entry_price": 329.757,
      "mark_price": 0.0,
      "unrealized_pnl": -452.090386,
      "position_value": 108293.04534,
      "leverage": {
        "type": "cross",
        "value": 10
      },
      "timestamp": "2025-03-25T15:16:46.222637"
    },
    {
      "coin": "kBONK",
      "size": -7417194.0,
      "entry_price": 0.013908,
      "mark_price": 0.0,
      "unrealized_pnl": -1921.251771,
      "position_value": 105086.804592,
      "leverage": {
        "type": "cross",
        "value": 10
      },
      "timestamp": "2025-03-25T15:16:46.222736"
    },
    {
      "coin": "TON",
      "size": -28815.6,
      "entry_price": 3.70625,
      "mark_price": 0.0,
      "unrealized_pnl": 1747.716047,
      "position_value": 105050.15136,
      "leverage": {
        "type": "cross",
        "value": 10
      },
      "timestamp": "2025-03-25T15:16:46.222700"
    },
    {
      "coin": "ZEREBRO",
      "size": -2610610.0,
      "entry_price": 0.039311,
      "mark_price": 0.0,
      "unrealized_pnl": -2077.176805,
      "position_value": 104703.73527,
      "leverage": {
        "type": "cross",
        "value": 5
      },
      "timestamp": "2025-03-25T15:16:46.222923"
    },
    {
      "coin": "GMX",
      "size": -7001.15,
      "entry_price": 14.5493,
      "mark_price": 0.0,
      "unrealized_pnl": 2606.553059,
      "position_value": 99255.30355,
      "leverage": {
        "type": "cross",
        "value": 3
      },
      "timestamp": "2025-03-25T15:16:46.222631"
    },
    {
      "coin": "ME",
      "size": 78916.8,
      "entry_price": 1.16813,
      "mark_price": 0.0,
      "unrealized_pnl": 4566.499782,
      "position_value": 96751.9968,
      "leverage": {
        "type": "cross",
        "value": 5
      },
      "timestamp": "2025-03-25T15:16:46.222901"
    },
    {
      "coin": "TRX",
      "size": -420419.0,
      "entry_price": 0.229207,
      "mark_price": 0.0,
      "unrealized_pnl": 599.989156,
      "position_value": 95763.03982,
      "leverage": {
        "type": "cross",
        "value": 10
      },
      "timestamp": "2025-03-25T15:16:46.222655"
    },
    {
      "coin": "FXS",
      "size": -45296.0,
      "entry_price": 2.12522,
      "mark_price": 0.0,
      "unrealized_pnl": 2129.870334,
      "position_value": 94134.1472,
      "leverage": {
        "type": "cross",
        "value": 5
      },
      "timestamp": "2025-03-25T15:16:46.222650"
    },
    {
      "coin": "FIL",
      "size": 30114.1,
      "entry_price": 3.03859,
      "mark_price": 0.0,
      "unrealized_pnl": 2454.563015,
      "position_value": 93959.00341,
      "leverage": {
        "type": "cross",
        "value": 5
      },
      "timestamp": "2025-03-25T15:16:46.222724"
    },
    {
      "coin": "NEIROETH",
      "size": -3463563.0,
      "entry_price": 0.030192,
      "mark_price": 0.0,
      "unrealized_pnl": 11438.314572,
      "position_value": 93135.20907,
      "leverage": {
        "type": "cross",
        "value": 5
      },
      "timestamp": "2025-03-25T15:16:46.222869"
    },
    {
      "coin": "ADA",
      "size": -113058.0,
      "entry_price": 0.758498,
      "mark_price": 0.0,
      "unrealized_pnl": 51.847171,
      "position_value": 85702.48632,
      "leverage": {
        "type": "cross",
        "value": 10
      },
      "timestamp": "2025-03-25T15:16:46.222697"
    },
    {
      "coin": "BIGTIME",
      "size": 1534923.0,
      "entry_price": 0.051164,
      "mark_price": 0.0,
      "unrealized_pnl": 3592.903377,
      "position_value": 82126.055115,
      "leverage": {
        "type": "cross",
        "value": 5
      },
      "timestamp": "2025-03-25T15:16:46.222682"
    },
    {
      "coin": "KAS",
      "size": -1020695.0,
      "entry_price": 0.077702,
      "mark_price": 0.0,
      "unrealized_pnl": -29.49439,
      "position_value": 79339.643045,
      "leverage": {
        "type": "cross",
        "value": 3
      },
      "timestamp": "2025-03-25T15:16:46.222684"
    },
    {
      "coin": "SCR",
      "size": 209061.4,
      "entry_price": 0.35623,
      "mark_price": 0.0,
      "unrealized_pnl": 4838.234044,
      "position_value": 79313.713932,
      "leverage": {
        "type": "cross",
        "value": 5
      },
      "timestamp": "2025-03-25T15:16:46.222866"
    },
    {
      "coin": "MEME",
      "size": 29144188.0,
      "entry_price": 0.00246,
      "mark_price": 0.0,
      "unrealized_pnl": 3445.118844,
      "position_value": 75162.860852,
      "leverage": {
        "type": "cross",
        "value": 5
      },
      "timestamp": "2025-03-25T15:16:46.222713"
    },
    {
      "coin": "NEAR",
      "size": -24421.0,
      "entry_price": 2.89618,
      "mark_price": 0.0,
      "unrealized_pnl": -2667.086561,
      "position_value": 73394.8734,
      "leverage": {
        "type": "cross",
        "value": 10
      },
      "timestamp": "2025-03-25T15:16:46.222710"
    },
    {
      "coin": "GOAT",
      "size": -1077298.0,
      "entry_price": 0.062353,
      "mark_price": 0.0,
      "unrealized_pnl": -372.103143,
      "position_value": 67545.507302,
      "leverage": {
        "type": "cross",
        "value": 5
      },
      "timestamp": "2025-03-25T15:16:46.222874"
    },
    {
      "coin": "SEI",
      "size": -313823.0,
      "entry_price": 0.205001,
      "mark_price": 0.0,
      "unrealized_pnl": -759.069502,
      "position_value": 65093.16666,
      "leverage": {
        "type": "cross",
        "value": 10
      },
      "timestamp": "2025-03-25T15:16:46.222665"
    },
    {
      "coin": "GRIFFAIN",
      "size": -1246167.0,
      "entry_price": 0.052089,
      "mark_price": 0.0,
      "unrealized_pnl": 676.506847,
      "position_value": 64236.170349,
      "leverage": {
        "type": "cross",
        "value": 5
      },
      "timestamp": "2025-03-25T15:16:46.222928"
    },
    {
      "coin": "XLM",
      "size": 219052.0,
      "entry_price": 0.282273,
      "mark_price": 0.0,
      "unrealized_pnl": 2321.11694,
      "position_value": 64153.75924,
      "leverage": {
        "type": "cross",
        "value": 5
      },
      "timestamp": "2025-03-25T15:16:46.222886"
    },
    {
      "coin": "PYTH",
      "size": 356096.0,
      "entry_price": 0.162829,
      "mark_price": 0.0,
      "unrealized_pnl": 3671.465378,
      "position_value": 61654.46144,
      "leverage": {
        "type": "cross",
        "value": 5
      },
      "timestamp": "2025-03-25T15:16:46.222726"
    },
    {
      "coin": "FET",
      "size": -105608.0,
      "entry_price": 0.56024,
      "mark_price": 0.0,
      "unrealized_pnl": 14.849556,
      "position_value": 59151.0408,
      "leverage": {
        "type": "cross",
        "value": 5
      },
      "timestamp": "2025-03-25T15:16:46.222708"
    },
    {
      "coin": "MEW",
      "size": 24005169.0,
      "entry_price": 0.002072,
      "mark_price": 0.0,
      "unrealized_pnl": 6727.713809,
      "position_value": 56484.162657,
      "leverage": {
        "type": "cross",
        "value": 5
      },
      "timestamp": "2025-03-25T15:16:46.222848"
    },
    {
      "coin": "RSR",
      "size": -7764037.0,
      "entry_price": 0.007357,
      "mark_price": 0.0,
      "unrealized_pnl": 831.369973,
      "position_value": 56289.26825,
      "leverage": {
        "type": "cross",
        "value": 3
      },
      "timestamp": "2025-03-25T15:16:46.222741"
    },
    {
      "coin": "TURBO",
      "size": 22259493.0,
      "entry_price": 0.00239,
      "mark_price": 0.0,
      "unrealized_pnl": 1556.019284,
      "position_value": 54758.35278,
      "leverage": {
        "type": "cross",
        "value": 5
      },
      "timestamp": "2025-03-25T15:16:46.222826"
    },
    {
      "coin": "GALA",
      "size": 2878251.0,
      "entry_price": 0.017442,
      "mark_price": 0.0,
      "unrealized_pnl": 2563.117219,
      "position_value": 52766.975583,
      "leverage": {
        "type": "cross",
        "value": 3
      },
      "timestamp": "2025-03-25T15:16:46.222744"
    },
    {
      "coin": "IO",
      "size": 57366.3,
      "entry_price": 0.87669,
      "mark_price": 0.0,
      "unrealized_pnl": 2381.028964,
      "position_value": 52673.73666,
      "leverage": {
        "type": "cross",
        "value": 5
      },
      "timestamp": "2025-03-25T15:16:46.222840"
    },
    {
      "coin": "UNI",
      "size": 7476.5,
      "entry_price": 6.93117,
      "mark_price": 0.0,
      "unrealized_pnl": 516.844196,
      "position_value": 52337.74295,
      "leverage": {
        "type": "cross",
        "value": 10
      },
      "timestamp": "2025-03-25T15:16:46.222663"
    },
    {
      "coin": "kNEIRO",
      "size": 174032.9,
      "entry_price": 0.27148,
      "mark_price": 0.0,
      "unrealized_pnl": 2932.631764,
      "position_value": 50180.646386,
      "leverage": {
        "type": "cross",
        "value": 5
      },
      "timestamp": "2025-03-25T15:16:46.222871"
    },
    {
      "coin": "VINE",
      "size": -1763337.0,
      "entry_price": 0.027491,
      "mark_price": 0.0,
      "unrealized_pnl": -42.019909,
      "position_value": 48518.217555,
      "leverage": {
        "type": "cross",
        "value": 5
      },
      "timestamp": "2025-03-25T15:16:46.222946"
    },
    {
      "coin": "CHILLGUY",
      "size": -1555968.0,
      "entry_price": 0.03028,
      "mark_price": 0.0,
      "unrealized_pnl": -1196.985278,
      "position_value": 48312.8064,
      "leverage": {
        "type": "cross",
        "value": 3
      },
      "timestamp": "2025-03-25T15:16:46.222889"
    },
    {
      "coin": "MYRO",
      "size": -2505801.0,
      "entry_price": 0.018063,
      "mark_price": 0.0,
      "unrealized_pnl": -2619.214093,
      "position_value": 47883.351309,
      "leverage": {
        "type": "cross",
        "value": 3
      },
      "timestamp": "2025-03-25T15:16:46.222789"
    },
    {
      "coin": "FTT",
      "size": 40118.0,
      "entry_price": 1.21447,
      "mark_price": 0.0,
      "unrealized_pnl": -1563.704238,
      "position_value": 47158.709,
      "leverage": {
        "type": "cross",
        "value": 3
      },
      "timestamp": "2025-03-25T15:16:46.222679"
    },
    {
      "coin": "ANIME",
      "size": -2373042.0,
      "entry_price": 0.019571,
      "mark_price": 0.0,
      "unrealized_pnl": -706.468994,
      "position_value": 47149.971498,
      "leverage": {
        "type": "cross",
        "value": 3
      },
      "timestamp": "2025-03-25T15:16:46.222944"
    },
    {
      "coin": "DYM",
      "size": -125338.9,
      "entry_price": 0.37189,
      "mark_price": 0.0,
      "unrealized_pnl": 1024.504664,
      "position_value": 45588.264708,
      "leverage": {
        "type": "cross",
        "value": 3
      },
      "timestamp": "2025-03-25T15:16:46.222772"
    },
    {
      "coin": "KAITO",
      "size": -32794.0,
      "entry_price": 1.339087,
      "mark_price": 0.0,
      "unrealized_pnl": 288.180571,
      "position_value": 43625.8582,
      "leverage": {
        "type": "cross",
        "value": 5
      },
      "timestamp": "2025-03-25T15:16:46.222964"
    },
    {
      "coin": "EIGEN",
      "size": -36938.13,
      "entry_price": 1.1428,
      "mark_price": 0.0,
      "unrealized_pnl": -309.794766,
      "position_value": 42523.175256,
      "leverage": {
        "type": "cross",
        "value": 5
      },
      "timestamp": "2025-03-25T15:16:46.222818"
    },
    {
      "coin": "REZ",
      "size": -2288643.0,
      "entry_price": 0.018526,
      "mark_price": 0.0,
      "unrealized_pnl": -43.134905,
      "position_value": 42442.884435,
      "leverage": {
        "type": "cross",
        "value": 3
      },
      "timestamp": "2025-03-25T15:16:46.222821"
    },
    {
      "coin": "CELO",
      "size": -106451.0,
      "entry_price": 0.371358,
      "mark_price": 0.0,
      "unrealized_pnl": -1928.999418,
      "position_value": 41460.53548,
      "leverage": {
        "type": "cross",
        "value": 3
      },
      "timestamp": "2025-03-25T15:16:46.222861"
    },
    {
      "coin": "GRASS",
      "size": -27629.4,
      "entry_price": 1.4708,
      "mark_price": 0.0,
      "unrealized_pnl": -265.167217,
      "position_value": 40902.56376,
      "leverage": {
        "type": "cross",
        "value": 5
      },
      "timestamp": "2025-03-25T15:16:46.222881"
    },
    {
      "coin": "NEO",
      "size": 5051.74,
      "entry_price": 8.1111,
      "mark_price": 0.0,
      "unrealized_pnl": -1036.250616,
      "position_value": 39939.05644,
      "leverage": {
        "type": "cross",
        "value": 5
      },
      "timestamp": "2025-03-25T15:16:46.222718"
    },
    {
      "coin": "BLUR",
      "size": 295308.0,
      "entry_price": 0.115465,
      "mark_price": 0.0,
      "unrealized_pnl": 579.998164,
      "position_value": 34678.01844,
      "leverage": {
        "type": "cross",
        "value": 5
      },
      "timestamp": "2025-03-25T15:16:46.222689"
    },
    {
      "coin": "BIO",
      "size": -347315.0,
      "entry_price": 0.094755,
      "mark_price": 0.0,
      "unrealized_pnl": -890.370464,
      "position_value": 33800.348485,
      "leverage": {
        "type": "cross",
        "value": 5
      },
      "timestamp": "2025-03-25T15:16:46.222925"
    },
    {
      "coin": "LAYER",
      "size": -23827.0,
      "entry_price": 0.88923,
      "mark_price": 0.0,
      "unrealized_pnl": -12215.38809,
      "position_value": 33403.0713,
      "leverage": {
        "type": "cross",
        "value": 3
      },
      "timestamp": "2025-03-25T15:16:46.222957"
    },
    {
      "coin": "STG",
      "size": -151178.0,
      "entry_price": 0.216804,
      "mark_price": 0.0,
      "unrealized_pnl": -425.574722,
      "position_value": 33201.71236,
      "leverage": {
        "type": "cross",
        "value": 3
      },
      "timestamp": "2025-03-25T15:16:46.222705"
    },
    {
      "coin": "ETHFI",
      "size": 45504.3,
      "entry_price": 0.66755,
      "mark_price": 0.0,
      "unrealized_pnl": 775.350115,
      "position_value": 31151.788737,
      "leverage": {
        "type": "cross",
        "value": 5
      },
      "timestamp": "2025-03-25T15:16:46.222797"
    },
    {
      "coin": "ETC",
      "size": -1648.64,
      "entry_price": 18.1552,
      "mark_price": 0.0,
      "unrealized_pnl": -279.917351,
      "position_value": 30211.328,
      "leverage": {
        "type": "cross",
        "value": 5
      },
      "timestamp": "2025-03-25T15:16:46.222759"
    },
    {
      "coin": "ZRO",
      "size": -10679.7,
      "entry_price": 2.77829,
      "mark_price": 0.0,
      "unrealized_pnl": -47.029792,
      "position_value": 29718.40119,
      "leverage": {
        "type": "cross",
        "value": 5
      },
      "timestamp": "2025-03-25T15:16:46.222671"
    },
    {
      "coin": "APE",
      "size": 50597.6,
      "entry_price": 0.55565,
      "mark_price": 0.0,
      "unrealized_pnl": 212.297195,
      "position_value": 28327.06636,
      "leverage": {
        "type": "cross",
        "value": 5
      },
      "timestamp": "2025-03-25T15:16:46.222596"
    },
    {
      "coin": "INJ",
      "size": 2676.8,
      "entry_price": 10.57346,
      "mark_price": 0.0,
      "unrealized_pnl": -33.37254,
      "position_value": 28269.6848,
      "leverage": {
        "type": "cross",
        "value": 10
      },
      "timestamp": "2025-03-25T15:16:46.222609"
    },
    {
      "coin": "ALGO",
      "size": -129769.0,
      "entry_price": 0.2016,
      "mark_price": 0.0,
      "unrealized_pnl": -879.733954,
      "position_value": 27041.26422,
      "leverage": {
        "type": "cross",
        "value": 3
      },
      "timestamp": "2025-03-25T15:16:46.222896"
    },
    {
      "coin": "ATOM",
      "size": 5488.75,
      "entry_price": 4.885,
      "mark_price": 0.0,
      "unrealized_pnl": -181.555395,
      "position_value": 26631.415,
      "leverage": {
        "type": "cross",
        "value": 5
      },
      "timestamp": "2025-03-25T15:16:46.222581"
    },
    {
      "coin": "ORDI",
      "size": 2633.45,
      "entry_price": 10.0746,
      "mark_price": 0.0,
      "unrealized_pnl": -25.484441,
      "position_value": 26505.67425,
      "leverage": {
        "type": "cross",
        "value": 5
      },
      "timestamp": "2025-03-25T15:16:46.222716"
    },
    {
      "coin": "STRK",
      "size": -145394.0,
      "entry_price": 0.17622,
      "mark_price": 0.0,
      "unrealized_pnl": 3.796571,
      "position_value": 25618.4228,
      "leverage": {
        "type": "cross",
        "value": 5
      },
      "timestamp": "2025-03-25T15:16:46.222778"
    },
    {
      "coin": "CFX",
      "size": -266655.0,
      "entry_price": 0.091828,
      "mark_price": 0.0,
      "unrealized_pnl": -200.448522,
      "position_value": 24686.9199,
      "leverage": {
        "type": "cross",
        "value": 5
      },
      "timestamp": "2025-03-25T15:16:46.222629"
    },
    {
      "coin": "MANTA",
      "size": 84736.3,
      "entry_price": 0.27219,
      "mark_price": 0.0,
      "unrealized_pnl": 708.687769,
      "position_value": 23773.616328,
      "leverage": {
        "type": "cross",
        "value": 3
      },
      "timestamp": "2025-03-25T15:16:46.222762"
    },
    {
      "coin": "PNUT",
      "size": -111137.5,
      "entry_price": 0.20842,
      "mark_price": 0.0,
      "unrealized_pnl": -81.066023,
      "position_value": 23244.408125,
      "leverage": {
        "type": "cross",
        "value": 5
      },
      "timestamp": "2025-03-25T15:16:46.222884"
    },
    {
      "coin": "IOTA",
      "size": -108989.0,
      "entry_price": 0.191173,
      "mark_price": 0.0,
      "unrealized_pnl": 2.59309,
      "position_value": 20833.24735,
      "leverage": {
        "type": "cross",
        "value": 3
      },
      "timestamp": "2025-03-25T15:16:46.222894"
    },
    {
      "coin": "DOT",
      "size": 4360.2,
      "entry_price": 4.63426,
      "mark_price": 0.0,
      "unrealized_pnl": 262.621603,
      "position_value": 20468.9589,
      "leverage": {
        "type": "cross",
        "value": 10
      },
      "timestamp": "2025-03-25T15:16:46.222673"
    },
    {
      "coin": "IMX",
      "size": -26602.7,
      "entry_price": 0.60103,
      "mark_price": 0.0,
      "unrealized_pnl": -944.140548,
      "position_value": 16933.416631,
      "leverage": {
        "type": "cross",
        "value": 5
      },
      "timestamp": "2025-03-25T15:16:46.222733"
    },
    {
      "coin": "OP",
      "size": 17221.7,
      "entry_price": 0.89872,
      "mark_price": 0.0,
      "unrealized_pnl": -55.690858,
      "position_value": 15421.860133,
      "leverage": {
        "type": "cross",
        "value": 10
      },
      "timestamp": "2025-03-25T15:16:46.222598"
    },
    {
      "coin": "OMNI",
      "size": -4325.72,
      "entry_price": 3.5708,
      "mark_price": 0.0,
      "unrealized_pnl": 463.943794,
      "position_value": 14982.563792,
      "leverage": {
        "type": "cross",
        "value": 3
      },
      "timestamp": "2025-03-25T15:16:46.222815"
    },
    {
      "coin": "ENS",
      "size": -796.32,
      "entry_price": 17.1263,
      "mark_price": 0.0,
      "unrealized_pnl": -551.543598,
      "position_value": 14189.62608,
      "leverage": {
        "type": "cross",
        "value": 5
      },
      "timestamp": "2025-03-25T15:16:46.222757"
    },
    {
      "coin": "SPX",
      "size": -20815.1,
      "entry_price": 0.61769,
      "mark_price": 0.0,
      "unrealized_pnl": -138.496177,
      "position_value": 12995.907685,
      "leverage": {
        "type": "cross",
        "value": 5
      },
      "timestamp": "2025-03-25T15:16:46.222930"
    },
    {
      "coin": "AR",
      "size": -1553.85,
      "entry_price": 7.5295,
      "mark_price": 0.0,
      "unrealized_pnl": -159.144037,
      "position_value": 11858.9832,
      "leverage": {
        "type": "cross",
        "value": 5
      },
      "timestamp": "2025-03-25T15:16:46.222787"
    },
    {
      "coin": "PIXEL",
      "size": 246242.0,
      "entry_price": 0.088274,
      "mark_price": 0.0,
      "unrealized_pnl": -12062.537317,
      "position_value": 9674.355696,
      "leverage": {
        "type": "cross",
        "value": 3
      },
      "timestamp": "2025-03-25T15:16:46.222780"
    },
    {
      "coin": "ALT",
      "size": 245731.0,
      "entry_price": 0.03914,
      "mark_price": 0.0,
      "unrealized_pnl": -48.120519,
      "position_value": 9569.993795,
      "leverage": {
        "type": "cross",
        "value": 5
      },
      "timestamp": "2025-03-25T15:16:46.222767"
    },
    {
      "coin": "ZEN",
      "size": -890.96,
      "entry_price": 9.5729,
      "mark_price": 0.0,
      "unrealized_pnl": -227.164859,
      "position_value": 8756.265784,
      "leverage": {
        "type": "cross",
        "value": 5
      },
      "timestamp": "2025-03-25T15:16:46.222721"
    },
    {
      "coin": "HMSTR",
      "size": 3801669.0,
      "entry_price": 0.002117,
      "mark_price": 0.0,
      "unrealized_pnl": -4.145303,
      "position_value": 8044.331604,
      "leverage": {
        "type": "cross",
        "value": 3
      },
      "timestamp": "2025-03-25T15:16:46.222863"
    },
    {
      "coin": "NOT",
      "size": 3066649.0,
      "entry_price": 0.002618,
      "mark_price": 0.0,
      "unrealized_pnl": -11.518574,
      "position_value": 8019.287135,
      "leverage": {
        "type": "cross",
        "value": 3
      },
      "timestamp": "2025-03-25T15:16:46.222823"
    },
    {
      "coin": "USUAL",
      "size": -53429.4,
      "entry_price": 0.17786,
      "mark_price": 0.0,
      "unrealized_pnl": 1817.133894,
      "position_value": 7685.81919,
      "leverage": {
        "type": "cross",
        "value": 5
      },
      "timestamp": "2025-03-25T15:16:46.222912"
    },
    {
      "coin": "kDOGS",
      "size": -38281.0,
      "entry_price": 0.164762,
      "mark_price": 0.0,
      "unrealized_pnl": 83.169929,
      "position_value": 6224.10779,
      "leverage": {
        "type": "cross",
        "value": 3
      },
      "timestamp": "2025-03-25T15:16:46.222853"
    },
    {
      "coin": "MOODENG",
      "size": 133675.0,
      "entry_price": 0.039332,
      "mark_price": 0.0,
      "unrealized_pnl": 53.255962,
      "position_value": 5311.041425,
      "leverage": {
        "type": "cross",
        "value": 5
      },
      "timestamp": "2025-03-25T15:16:46.222876"
    },
    {
      "coin": "BOME",
      "size": 3284673.0,
      "entry_price": 0.001561,
      "mark_price": 0.0,
      "unrealized_pnl": 97.890365,
      "position_value": 5225.914743,
      "leverage": {
        "type": "cross",
        "value": 3
      },
      "timestamp": "2025-03-25T15:16:46.222795"
    },
    {
      "coin": "CATI",
      "size": -34351.0,
      "entry_price": 0.147995,
      "mark_price": 0.0,
      "unrealized_pnl": 17.035954,
      "position_value": 5066.7725,
      "leverage": {
        "type": "cross",
        "value": 3
      },
      "timestamp": "2025-03-25T15:16:46.222858"
    },
    {
      "coin": "WLD",
      "size": -3707.6,
      "entry_price": 0.91864,
      "mark_price": 0.0,
      "unrealized_pnl": -14.273476,
      "position_value": 3420.223924,
      "leverage": {
        "type": "cross",
        "value": 10
      },
      "timestamp": "2025-03-25T15:16:46.222648"
    },
    {
      "coin": "PEOPLE",
      "size": 103359.0,
      "entry_price": 0.018071,
      "mark_price": 0.0,
      "unrealized_pnl": -6.358503,
      "position_value": 1861.49559,
      "leverage": {
        "type": "cross",
        "value": 3
      },
      "timestamp": "2025-03-25T15:16:46.222754"
    },
    {
      "coin": "BSV",
      "size": 38.67,
      "entry_price": 35.0071,
      "mark_price": 0.0,
      "unrealized_pnl": -5.806116,
      "position_value": 1347.92019,
      "leverage": {
        "type": "cross",
        "value": 3
      },
      "timestamp": "2025-03-25T15:16:46.222695"
    },
    {
      "coin": "TNSR",
      "size": -6126.1,
      "entry_price": 0.21237,
      "mark_price": 0.0,
      "unrealized_pnl": 11.271751,
      "position_value": 1289.789094,
      "leverage": {
        "type": "cross",
        "value": 3
      },
      "timestamp": "2025-03-25T15:16:46.222803"
    },
    {
      "coin": "STX",
      "size": -1168.9,
      "entry_price": 0.69006,
      "mark_price": 0.0,
      "unrealized_pnl": -2.625639,
      "position_value": 809.241159,
      "leverage": {
        "type": "cross",
        "value": 5
      },
      "timestamp": "2025-03-25T15:16:46.222626"
    },
    {
      "coin": "YGG",
      "size": -2133.0,
      "entry_price": 0.278258,
      "mark_price": 0.0,
      "unrealized_pnl": 142.82247,
      "position_value": 450.7029,
      "leverage": {
        "type": "cross",
        "value": 3
      },
      "timestamp": "2025-03-25T15:16:46.222653"
    },
    {
      "coin": "MERL",
      "size": -3825.0,
      "entry_price": 0.262727,
      "mark_price": 0.0,
      "unrealized_pnl": 557.753195,
      "position_value": 447.18075,
      "leverage": {
        "type": "cross",
        "value": 3
      },
      "timestamp": "2025-03-25T15:16:46.222808"
    },
    {
      "coin": "ORBS",
      "size": -17536.0,
      "entry_price": 0.028282,
      "mark_price": 0.0,
      "unrealized_pnl": 153.842218,
      "position_value": 342.12736,
      "leverage": {
        "type": "cross",
        "value": 3
      },
      "timestamp": "2025-03-25T15:16:46.222687"
    },
    {
      "coin": "TST",
      "size": -2993.0,
      "entry_price": 0.067603,
      "mark_price": 0.0,
      "unrealized_pnl": 2.358484,
      "position_value": 199.977295,
      "leverage": {
        "type": "cross",
        "value": 3
      },
      "timestamp": "2025-03-25T15:16:46.222954"
    },
    {
      "coin": "PENDLE",
      "size": -41.0,
      "entry_price": 2.8983,
      "mark_price": 0.0,
      "unrealized_pnl": -0.4059,
      "position_value": 119.2362,
      "leverage": {
        "type": "cross",
        "value": 5
      },
      "timestamp": "2025-03-25T15:16:46.222702"
    },
    {
      "coin": "TRB",
      "size": 2.64,
      "entry_price": 30.91,
      "mark_price": 0.0,
      "unrealized_pnl": -0.51216,
      "position_value": 81.09024,
      "leverage": {
        "type": "cross",
        "value": 3
      },
      "timestamp": "2025-03-25T15:16:46.222676"
    }
  ],
  "total_position_value": 30849299.305122014,
  "total_unrealized_pnl": -137770.318327,
  "account_value": 13454295.74,
  "roi": 22.65,
  "timestamp": "2025-03-25T15:16:46.225807"
}