{
  "address": "0x985fc4485570d0c4763dc5414b3f9dbf0e0f28aa",
  "positions": [
    {
      "coin": "AVAX",
      "size": 12069.31,
      "entry_price": 21.0934,
      "mark_price": 0.0,
      "unrealized_pnl": 19087.919244,
      "position_value": 273671.60425,
      "leverage": {
        "type": "cross",
        "value": 10
      },
      "timestamp": "2025-03-26T10:48:07.566225"
    },
    {
      "coin": "LINK",
      "size": 14390.8,
      "entry_price": 16.55413,
      "mark_price": 0.0,
      "unrealized_pnl": -9557.463157,
      "position_value": 228669.812,
      "leverage": {
        "type": "cross",
        "value": 10
      },
      "timestamp": "2025-03-26T10:48:07.566236"
    },
    {
      "coin": "ENA",
      "size": 485011.0,
      "entry_price": 0.389249,
      "mark_price": 0.0,
      "unrealized_pnl": 17582.000924,
      "position_value": 206372.1805,
      "leverage": {
        "type": "cross",
        "value": 10
      },
      "timestamp": "2025-03-26T10:48:07.566253"
    },
    {
      "coin": "BNB",
      "size": 281.225,
      "entry_price": 626.883,
      "mark_price": 0.0,
      "unrealized_pnl": 862.245003,
      "position_value": 177157.68875,
      "leverage": {
        "type": "cross",
        "value": 10
      },
      "timestamp": "2025-03-26T10:48:07.566232"
    },
    {
      "coin": "MKR",
      "size": 118.2504,
      "entry_price": 1284.11,
      "mark_price": 0.0,
      "unrealized_pnl": 5709.715889,
      "position_value": 157556.83296,
      "leverage": {
        "type": "cross",
        "value": 10
      },
      "timestamp": "2025-03-26T10:48:07.566243"
    },
    {
      "coin": "JTO",
      "size": 51081.0,
      "entry_price": 2.586313,
      "mark_price": 0.0,
      "unrealized_pnl": -5175.171562,
      "position_value": 126936.285,
      "leverage": {
        "type": "cross",
        "value": 5
      },
      "timestamp": "2025-03-26T10:48:07.566250"
    },
    {
      "coin": "AAVE",
      "size": 668.6,
      "entry_price": 209.0536,
      "mark_price": 0.0,
      "unrealized_pnl": -14845.357728,
      "position_value": 124927.91,
      "leverage": {
        "type": "cross",
        "value": 10
      },
      "timestamp": "2025-03-26T10:48:07.566240"
    },
    {
      "coin": "TRX",
      "size": 476744.0,
      "entry_price": 0.237189,
      "mark_price": 0.0,
      "unrealized_pnl": -3551.716678,
      "position_value": 109527.16656,
      "leverage": {
        "type": "cross",
        "value": 10
      },
      "timestamp": "2025-03-26T10:48:07.566246"
    },
    {
      "coin": "KAITO",
      "size": 76908.0,
      "entry_price": 1.634182,
      "mark_price": 0.0,
      "unrealized_pnl": -21340.65959,
      "position_value": 104341.0836,
      "leverage": {
        "type": "cross",
        "value": 5
      },
      "timestamp": "2025-03-26T10:48:07.566256"
    }
  ],
  "total_position_value": 1509160.56362,
  "total_unrealized_pnl": -11228.487654999997,
  "account_value": 2125401.85,
  "roi": 121.45,
  "timestamp": "2025-03-26T10:48:07.568442"
}