{
  "address": "0xb0fbfefc6c325964d0ffc3f909bdda80b8421326",
  "positions": [
    {
      "coin": "SOL",
      "size": -2750.0,
      "entry_price": 141.4925,
      "mark_price": 0.0,
      "unrealized_pnl": -12367.998038,
      "position_value": 401472.5,
      "leverage": {
        "type": "cross",
        "value": 20
      },
      "timestamp": "2025-03-25T15:16:49.467146"
    },
    {
      "coin": "FARTCOIN",
      "size": -580000.0,
      "entry_price": 0.40134,
      "mark_price": 0.0,
      "unrealized_pnl": -92574.936593,
      "position_value": 325356.8,
      "leverage": {
        "type": "cross",
        "value": 3
      },
      "timestamp": "2025-03-25T15:16:49.467201"
    },
    {
      "coin": "S",
      "size": -380000.0,
      "entry_price": 0.569176,
      "mark_price": 0.0,
      "unrealized_pnl": -17298.951725,
      "position_value": 233586.0,
      "leverage": {
        "type": "cross",
        "value": 5
      },
      "timestamp": "2025-03-25T15:16:49.467205"
    },
    {
      "coin": "NIL",
      "size": -280000.0,
      "entry_price": 0.763771,
      "mark_price": 0.0,
      "unrealized_pnl": 15817.7092,
      "position_value": 198038.4,
      "leverage": {
        "type": "cross",
        "value": 3
      },
      "timestamp": "2025-03-25T15:16:49.467218"
    },
    {
      "coin": "CRV",
      "size": -380000.0,
      "entry_price": 0.43992,
      "mark_price": 0.0,
      "unrealized_pnl": -25094.171308,
      "position_value": 192264.8,
      "leverage": {
        "type": "cross",
        "value": 10
      },
      "timestamp": "2025-03-25T15:16:49.467155"
    },
    {
      "coin": "MKR",
      "size": -120.0,
      "entry_price": 1232.36,
      "mark_price": 0.0,
      "unrealized_pnl": -3712.73747,
      "position_value": 151596.0,
      "leverage": {
        "type": "cross",
        "value": 10
      },
      "timestamp": "2025-03-25T15:16:49.467165"
    },
    {
      "coin": "BTC",
      "size": -1.68,
      "entry_price": 84690.1,
      "mark_price": 0.0,
      "unrealized_pnl": -5175.876731,
      "position_value": 147455.28,
      "leverage": {
        "type": "cross",
        "value": 20
      },
      "timestamp": "2025-03-25T15:16:49.467131"
    },
    {
      "coin": "GOAT",
      "size": -2080000.0,
      "entry_price": 0.060053,
      "mark_price": 0.0,
      "unrealized_pnl": -5512.401194,
      "position_value": 130424.32,
      "leverage": {
        "type": "cross",
        "value": 5
      },
      "timestamp": "2025-03-25T15:16:49.467196"
    },
    {
      "coin": "RENDER",
      "size": -30000.0,
      "entry_price": 3.69654,
      "mark_price": 0.0,
      "unrealized_pnl": -11434.75926,
      "position_value": 122331.0,
      "leverage": {
        "type": "cross",
        "value": 5
      },
      "timestamp": "2025-03-25T15:16:49.467192"
    },
    {
      "coin": "POPCAT",
      "size": -480000.0,
      "entry_price": 0.211488,
      "mark_price": 0.0,
      "unrealized_pnl": -18432.508476,
      "position_value": 119947.2,
      "leverage": {
        "type": "cross",
        "value": 5
      },
      "timestamp": "2025-03-25T15:16:49.467187"
    },
    {
      "coin": "KAITO",
      "size": -88000.0,
      "entry_price": 1.369312,
      "mark_price": 0.0,
      "unrealized_pnl": 3459.471,
      "position_value": 117040.0,
      "leverage": {
        "type": "cross",
        "value": 5
      },
      "timestamp": "2025-03-25T15:16:49.467213"
    },
    {
      "coin": "HBAR",
      "size": -480000.0,
      "entry_price": 0.203684,
      "mark_price": 0.0,
      "unrealized_pnl": 2147.710629,
      "position_value": 95620.8,
      "leverage": {
        "type": "cross",
        "value": 5
      },
      "timestamp": "2025-03-25T15:16:49.467183"
    },
    {
      "coin": "BCH",
      "size": -280.0,
      "entry_price": 332.499,
      "mark_price": 0.0,
      "unrealized_pnl": 391.81504,
      "position_value": 92708.0,
      "leverage": {
        "type": "cross",
        "value": 10
      },
      "timestamp": "2025-03-25T15:16:49.467160"
    },
    {
      "coin": "ETH",
      "size": -42.5,
      "entry_price": 2008.41,
      "mark_price": 0.0,
      "unrealized_pnl": -2409.055117,
      "position_value": 87766.75,
      "leverage": {
        "type": "cross",
        "value": 20
      },
      "timestamp": "2025-03-25T15:16:49.467140"
    },
    {
      "coin": "kPEPE",
      "size": -8000000.0,
      "entry_price": 0.007968,
      "mark_price": 0.0,
      "unrealized_pnl": 30.568872,
      "position_value": 63720.0,
      "leverage": {
        "type": "cross",
        "value": 10
      },
      "timestamp": "2025-03-25T15:16:49.467151"
    },
    {
      "coin": "JUP",
      "size": -100000.0,
      "entry_price": 0.538177,
      "mark_price": 0.0,
      "unrealized_pnl": -3824.23913,
      "position_value": 57642.0,
      "leverage": {
        "type": "cross",
        "value": 10
      },
      "timestamp": "2025-03-25T15:16:49.467169"
    },
    {
      "coin": "JTO",
      "size": -23000.0,
      "entry_price": 2.264058,
      "mark_price": 0.0,
      "unrealized_pnl": -2234.2486,
      "position_value": 54307.6,
      "leverage": {
        "type": "cross",
        "value": 5
      },
      "timestamp": "2025-03-25T15:16:49.467174"
    },
    {
      "coin": "WIF",
      "size": -100000.0,
      "entry_price": 0.54365,
      "mark_price": 0.0,
      "unrealized_pnl": 311.01957,
      "position_value": 54054.0,
      "leverage": {
        "type": "cross",
        "value": 10
      },
      "timestamp": "2025-03-25T15:16:49.467178"
    },
    {
      "coin": "JELLY",
      "size": -2800000.0,
      "entry_price": 0.036437,
      "mark_price": 0.0,
      "unrealized_pnl": 63908.651063,
      "position_value": 38116.4,
      "leverage": {
        "type": "cross",
        "value": 3
      },
      "timestamp": "2025-03-25T15:16:49.467209"
    }
  ],
  "total_position_value": 2683447.8499999996,
  "total_unrealized_pnl": -114004.938268,
  "account_value": 1122671.16,
  "roi": 87.94,
  "timestamp": "2025-03-25T15:16:49.467660"
}